HW1_CURR/HW1_CURR.py
HW1_CURR/__init__.py
HW1_CURR-0.2.0.dist-info/METADATA
HW1_CURR-0.2.0.dist-info/WHEEL
HW1_CURR-0.2.0.dist-info/top_level.txt
HW1_CURR-0.2.0.dist-info/RECORD
